{
  "lastChecks": {
    "weather": 1773878920
  },
  "weather": {
    "location": "Beijing",
    "lastReportDate": "2026-03-20",
    "lastReportTs": 1773929760,
    "lastReportLocalTime": "2026-03-20 08:36 CST",
    "snapshots": {
      "2026-03-19": {
        "location": "Beijing",
        "condition": "Sunny",
        "currentTempC": 0,
        "feelsLikeC": -1,
        "highTempC": 16,
        "lowTempC": 4,
        "rain": false,
        "rainChance": 0,
        "windKmph": 4,
        "humidity": 74,
        "summary": "Sunny, 0°C, feels like -1°C, 4-16°C, no rain"
      },
      "2026-03-20": {
        "location": "Beijing",
        "condition": "Overcast",
        "currentTempC": 6.7,
        "feelsLikeC": 2.7,
        "highTempC": 15,
        "lowTempC": 5,
        "rain": false,
        "rainChance": 0,
        "windKmph": 6,
        "humidity": 32,
        "summary": "Overcast, 6.7°C, feels like 2.7°C, 5-15°C, no rain"
      }
    }
  }
}
